ainconv/__init__.py
ainconv/detection.py
ainconv/syllable.py
ainconv/utils.py
ainconv/conversion/cyrillic.py
ainconv/conversion/katakana.py
ainconv/conversion/latin.py
ainconv-0.8.0.dist-info/LICENSE
ainconv-0.8.0.dist-info/METADATA
ainconv-0.8.0.dist-info/WHEEL
ainconv-0.8.0.dist-info/top_level.txt
ainconv-0.8.0.dist-info/RECORD
