Metadata-Version: 2.1
Name: ainconv
Version: 0.8.0
Summary: Converts Ainu text between different scripts (Katakana, Latin, Cyrillic and more)
Author-email: mkpoli <mkpoli@mkpo.li>
License: MIT License
Project-URL: repository, https://github.com/mkpoli/ainconv
Project-URL: documentation, https://ainconv-py.readthedocs.io/en/latest/
Keywords: ainu,converter,katakana,latin,cyrillic,language,writing system,text preprocessing
Classifier: Development Status :: 3 - Alpha
Classifier: Intended Audience :: Developers
Classifier: Intended Audience :: Information Technology
Classifier: Intended Audience :: Science/Research
Classifier: License :: OSI Approved :: MIT License
Classifier: Topic :: Text Processing
Requires-Python: <4.0,>=3.9
License-File: LICENSE
Requires-Dist: more-itertools<11.0.0,>=10.2.0
